MM22025UNO/__init__.py
MM22025UNO/lineales.py
MM22025UNO/no_lineales.py
MM22025UNO-0.1.6.dist-info/LICENSE
MM22025UNO-0.1.6.dist-info/METADATA
MM22025UNO-0.1.6.dist-info/WHEEL
MM22025UNO-0.1.6.dist-info/top_level.txt
MM22025UNO-0.1.6.dist-info/RECORD
