Metadata-Version: 2.1
Name: MM22025UNO
Version: 0.1.6
Summary: Librería para resolver sistemas de ecuaciones lineales y no lineales
Home-page: https://github.com/Robertmez03/MM22025UNO
Author: Roberto Mena
Author-email: mm22025@ues.edu.sv
License: MIT
Classifier: Programming Language :: Python :: 3
Classifier: License :: OSI Approved :: MIT License
License-File: LICENSE
Requires-Dist: numpy
Requires-Dist: scipy
